RcToolBox/__init__.py
RcToolBox/basic_op.py
RcToolBox/multiproc_op.py
RcToolBox/nifti_op.py
RcToolBox/pandas_op.py
rctoolbox-1.0.dist-info/METADATA
rctoolbox-1.0.dist-info/WHEEL
rctoolbox-1.0.dist-info/top_level.txt
rctoolbox-1.0.dist-info/RECORD
