Metadata-Version: 2.4
Name: RcToolBox
Version: 1.0
Summary: RC personal ToolBox
Home-page: 
Author: RC
Author-email: yilingyaomeng@gmail.com
License: MIT
Keywords: pip,RcToolBox
Platform: any
Requires-Dist: numpy==1.26.4
Requires-Dist: PyYAML==6.0.2
Requires-Dist: SimpleITK==2.4.0
Requires-Dist: pathos==0.3.4
Requires-Dist: pandas==2.2.3
Requires-Dist: openpyxl==3.1.5
Dynamic: author
Dynamic: author-email
Dynamic: description
Dynamic: keywords
Dynamic: license
Dynamic: platform
Dynamic: requires-dist
Dynamic: summary
